{"key":"fj","count":9,"entries":[{"w":"fj","s":"fj","p":"","t":"n. 斐济","d":"","pos":"","tag":"","bnc":45004,"frq":"","forms":[]},{"w":"fjall","s":"fjall","p":"[fjæl]","t":"[瑞]冰蚀高原","d":"","pos":"","tag":"","bnc":"","frq":"","forms":[]},{"w":"fjard","s":"fjard","p":"[fjɑ:d]","t":"低浅峡湾, 伙崖谷, (北欧诸国的)荒瘠高原[石质高原]","d":"","pos":"","tag":"","bnc":"","frq":"","forms":[]},{"w":"fjeld","s":"fjeld","p":"[fjeld]","t":"n. (北欧等的)冰蚀高原","d":"","pos":"","tag":"","bnc":"","frq":"","forms":[]},{"w":"fjeldbotn","s":"fjeldbotn","p":"['fjeldbәtn]","t":"[挪]冰蚀冰斗","d":"","pos":"","tag":"","bnc":"","frq":"","forms":[]},{"w":"fjelde","s":"fjelde","p":"","t":"[地名] [丹麦] 菲耶勒","d":"","pos":"","tag":"","bnc":"","frq":"","forms":[]},{"w":"fjell","s":"fjell","p":"[fjel]","t":"冰蚀沼地","d":"","pos":"","tag":"","bnc":"","frq":"","forms":[]},{"w":"fjord","s":"fjord","p":"[fjɔ:d]","t":"n. 峡湾","d":"n. a long narrow inlet of the sea between steep cliffs; common in Norway","pos":"","tag":"","bnc":24457,"frq":21776,"forms":["复数：fjords"]},{"w":"fjords","s":"fjords","p":"[fjɔ:dz]","t":"n. 峡湾, 海岸峡江( fjord的复数形式 )","d":"n. a long narrow inlet of the sea between steep cliffs; common in Norway","pos":"","tag":"","bnc":"","frq":"","forms":["原形：fjord","当前词形：复数"]}]}
