{"key":"n2","count":3,"entries":[{"w":"N-(2-chloroethyl)bibenzylamine hydrochloride","s":"n2chloroethylbibenzylaminehydrochloride","p":"","t":"[化] N-(2-氯乙基)二苄胺盐酸盐","d":"","pos":"","tag":"","bnc":"","frq":"","forms":[]},{"w":"N,2-formylsulfisomidine","s":"n2formylsulfisomidine","p":"","t":"[化] 甲酰磺胺异二甲嘧啶","d":"","pos":"","tag":"","bnc":"","frq":"","forms":[]},{"w":"N-2 gas tank pressurizing unit","s":"n2gastankpressurizingunit","p":"","t":"[化] 氮气罐压力装置","d":"","pos":"","tag":"","bnc":"","frq":"","forms":[]}]}
